eleos/__init__.py
eleos/__main__.py
eleos/constants.py
eleos/cores.py
eleos/mcmc.py
eleos/parsers.py
eleos/profiles.py
eleos/results.py
eleos/shapes.py
eleos/spectra.py
eleos/spx.py
eleos/utils.py
eleos/data/radtran_ids.csv
eleos/data/jupiter/c2h2apr.dat
eleos/data/jupiter/c2h6apr.dat
eleos/data/jupiter/fcloud.ref
eleos/data/jupiter/jupiter.ref
eleos/data/jupiter/miri.kls
eleos/data/jupiter/nirspec.kls
eleos/data/jupiter/parah2.ref
eleos/data/jupiter/tempapr.dat
eleos/data/misc/H3p_G395H_model.txt
eleos/data/misc/ch4_emission.csv
eleos/data/statics/nemesis.abo
eleos/data/statics/nemesis.inp
eleos/data/statics/nemesis.nam
eleos/data/statics/nemesis.set
eleos/data/statics/template.job
nemesis_eleos-0.9.16.dist-info/licenses/LICENSE
nemesis_eleos-0.9.16.dist-info/METADATA
nemesis_eleos-0.9.16.dist-info/WHEEL
nemesis_eleos-0.9.16.dist-info/top_level.txt
nemesis_eleos-0.9.16.dist-info/RECORD
