Metadata-Version: 2.4
Name: nemesis_eleos
Version: 0.9.16
Summary: A Python interface to the NEMESIS spectral inversion tool
Author-email: Simon Toogood <scat2@leicester.ac.uk>
License: MIT License
Project-URL: Homepage, https://github.com/simon-toogood/eleos
Project-URL: Documentation, https://eleos.readthedocs.io
Classifier: Programming Language :: Python :: 3
Classifier: License :: OSI Approved :: MIT License
Classifier: Operating System :: OS Independent
Requires-Python: >=3.9
License-File: LICENSE
Requires-Dist: pandas
Requires-Dist: matplotlib
Requires-Dist: numpy
Requires-Dist: scipy
Requires-Dist: astropy
Requires-Dist: planetmapper
Requires-Dist: h3ppy
Requires-Dist: emcee
Requires-Dist: h5py
Dynamic: license-file
